{
	"table": "entidade",
	"column": "entidade",
	"space": 10,
	"dependencies": [

		{
			"table": "coordenadoria",
			"column": "entidade"
		},
		{
			"table": "diretoria",
			"column": "entidade"
		},
		{
			"table": "entidade",
			"column": "entidade"
		},
		{
			"table": "entidade",
			"column": "entidadeorcamento"
		},
		{
			"table": "entidade",
			"column": "entidadeprincipal"
		},
		{
			"table": "exercicio",
			"column": "entidade"
		},
		{
			"table": "exercicio_mes",
			"column": "entidade"
		},
		{
			"table": "locais",
			"column": "entidade"
		},
		{
			"table": "origem",
			"column": "entidade"
		},
		{
			"table": "parametros",
			"column": "entidade"
		},
		{
			"table": "proc_correcaofluxo",
			"column": "entidade"
		},
		{
			"table": "processos",
			"column": "entidade"
		},
		{
			"table": "registro",
			"column": "entidade"
		},
		{
			"table": "registro",
			"column": "qtdentidades"
		},
		{
			"table": "tramitacao",
			"column": "entidade"
		},
		{
			"table": "unidade",
			"column": "entidade"
		},
		{
			"table": "unidadeorcamentaria",
			"column": "entidade"
		},
		{
			"table": "usuario_entidade",
			"column": "entidade"
		},
		{
			"table": "usuario_local",
			"column": "entidade"
		},
		{
			"table": "usuariolog",
			"column": "entidade"
		}
	]
},